{
  "id": "4444210",
  "name": "GeekSportAPP",
  "font_family": "iconfont",
  "css_prefix_text": "icon-",
  "description": "",
  "glyphs": [
    {
      "icon_id": "19500560",
      "name": "Square",
      "font_class": "rxa-heart-message-filled",
      "unicode": "e7ba",
      "unicode_decimal": 59322
    },
    {
      "icon_id": "19500564",
      "name": "Square",
      "font_class": "rxa-heart-message-lined",
      "unicode": "e7bb",
      "unicode_decimal": 59323
    },
    {
      "icon_id": "670112",
      "name": "Personal",
      "font_class": "yduigerenzhongxin",
      "unicode": "e68a",
      "unicode_decimal": 59018
    },
    {
      "icon_id": "670191",
      "name": "Home",
      "font_class": "yduizhuye",
      "unicode": "e6a0",
      "unicode_decimal": 59040
    },
    {
      "icon_id": "688334",
      "name": "Home-in",
      "font_class": "yduizhuyexuanzhong",
      "unicode": "e6b1",
      "unicode_decimal": 59057
    },
    {
      "icon_id": "670111",
      "name": "Personal-in",
      "font_class": "yduigerenzhongxinxuanzhong",
      "unicode": "e689",
      "unicode_decimal": 59017
    },
    {
      "icon_id": "39334077",
      "name": "Find-in",
      "font_class": "faxian1-copy",
      "unicode": "fb9a",
      "unicode_decimal": 64410
    },
    {
      "icon_id": "39333981",
      "name": "Expert",
      "font_class": "daren-copy",
      "unicode": "fb95",
      "unicode_decimal": 64405
    },
    {
      "icon_id": "39333969",
      "name": "navigation",
      "font_class": "daohang-copy",
      "unicode": "fb93",
      "unicode_decimal": 64403
    },
    {
      "icon_id": "435936",
      "name": "comment",
      "font_class": "pinglun",
      "unicode": "e7bf",
      "unicode_decimal": 59327
    },
    {
      "icon_id": "706797",
      "name": "football",
      "font_class": "zuqiu-copy",
      "unicode": "e619",
      "unicode_decimal": 58905
    },
    {
      "icon_id": "868799",
      "name": "arrow",
      "font_class": "jiantou",
      "unicode": "e65e",
      "unicode_decimal": 58974
    },
    {
      "icon_id": "947138",
      "name": "telephone",
      "font_class": "dianhua",
      "unicode": "e6a9",
      "unicode_decimal": 59049
    },
    {
      "icon_id": "967930",
      "name": "tennis",
      "font_class": "wangqiu",
      "unicode": "e651",
      "unicode_decimal": 58961
    },
    {
      "icon_id": "1625596",
      "name": "moon",
      "font_class": "yueliang",
      "unicode": "e62a",
      "unicode_decimal": 58922
    },
    {
      "icon_id": "4608975",
      "name": "sun",
      "font_class": "taiyangtianqi",
      "unicode": "e60d",
      "unicode_decimal": 58893
    },
    {
      "icon_id": "4988154",
      "name": "layerIn",
      "font_class": "tuceng1",
      "unicode": "e63e",
      "unicode_decimal": 58942
    },
    {
      "icon_id": "5171407",
      "name": "basketball",
      "font_class": "lanqiu",
      "unicode": "e624",
      "unicode_decimal": 58916
    },
    {
      "icon_id": "5628461",
      "name": "contacts",
      "font_class": "zujian-lianxiren",
      "unicode": "e607",
      "unicode_decimal": 58887
    },
    {
      "icon_id": "6486533",
      "name": "telephoneIn",
      "font_class": "dianhua1",
      "unicode": "e60b",
      "unicode_decimal": 58891
    },
    {
      "icon_id": "8282004",
      "name": "Promotion",
      "font_class": "tuiguangshouyi",
      "unicode": "e615",
      "unicode_decimal": 58901
    },
    {
      "icon_id": "8687733",
      "name": "score",
      "font_class": "pingfen",
      "unicode": "e69d",
      "unicode_decimal": 59037
    },
    {
      "icon_id": "9218584",
      "name": "ExpertIn",
      "font_class": "daren",
      "unicode": "e691",
      "unicode_decimal": 59025
    },
    {
      "icon_id": "9686779",
      "name": "Find",
      "font_class": "faxian",
      "unicode": "e616",
      "unicode_decimal": 58902
    },
    {
      "icon_id": "10340078",
      "name": "guidance",
      "font_class": "yiduiyizhidao",
      "unicode": "e667",
      "unicode_decimal": 58983
    },
    {
      "icon_id": "10471942",
      "name": "feedback",
      "font_class": "yjfk",
      "unicode": "e61d",
      "unicode_decimal": 58909
    },
    {
      "icon_id": "11465026",
      "name": "setup",
      "font_class": "shezhi",
      "unicode": "e64e",
      "unicode_decimal": 58958
    },
    {
      "icon_id": "12401499",
      "name": "field",
      "font_class": "changdi",
      "unicode": "e732",
      "unicode_decimal": 59186
    },
    {
      "icon_id": "14197345",
      "name": "writing",
      "font_class": "zhinengxiezuo",
      "unicode": "e60c",
      "unicode_decimal": 58892
    },
    {
      "icon_id": "16978108",
      "name": "plan",
      "font_class": "S_yundongjihuatiaozhuandizhi",
      "unicode": "e66d",
      "unicode_decimal": 58989
    },
    {
      "icon_id": "18564905",
      "name": "navigationIn",
      "font_class": "daohang",
      "unicode": "e617",
      "unicode_decimal": 58903
    },
    {
      "icon_id": "22049428",
      "name": "curriculum",
      "font_class": "kecheng",
      "unicode": "e601",
      "unicode_decimal": 58881
    },
    {
      "icon_id": "24111519",
      "name": "CheckIn",
      "font_class": "dakaqiandao",
      "unicode": "faa8",
      "unicode_decimal": 64168
    },
    {
      "icon_id": "24111759",
      "name": "welfare",
      "font_class": "fuli",
      "unicode": "fb92",
      "unicode_decimal": 64402
    },
    {
      "icon_id": "27340852",
      "name": "invite",
      "font_class": "yaoqinghaoyou",
      "unicode": "e68e",
      "unicode_decimal": 59022
    },
    {
      "icon_id": "27856934",
      "name": "contact",
      "font_class": "lianxidan",
      "unicode": "e669",
      "unicode_decimal": 58985
    },
    {
      "icon_id": "27992080",
      "name": "share",
      "font_class": "fenxiang",
      "unicode": "e6e6",
      "unicode_decimal": 59110
    },
    {
      "icon_id": "28563037",
      "name": "scan",
      "font_class": "a-saoma_scan-code1",
      "unicode": "e64c",
      "unicode_decimal": 58956
    },
    {
      "icon_id": "32239356",
      "name": "writingIn",
      "font_class": "xiezuo",
      "unicode": "e659",
      "unicode_decimal": 58969
    },
    {
      "icon_id": "39333971",
      "name": "telephoneCopy",
      "font_class": "dianhua-copy",
      "unicode": "fb94",
      "unicode_decimal": 64404
    }
  ]
}
